<?xml version="1.0" encoding="utf-8"?>
<ThermalLabel Version="8.0" Width="9" Height="7" GapLength="0" MarkLength="0" OffsetLength="0" UnitType="Cm" LabelsPerRow="1" LabelsHorizontalGapLength="0" IsContinuous="False" PrintSpeed="" PrintMirror="False" CutAfterPrinting="False">
  <Items>
    <RectangleShapeItem Name="" X="0.3287" Y="0.1497" DataField="" DataFieldFormatString="" CacheItemId="" Comments="" Tag="" Width="8.445" Height="6.4246" StrokeThickness="0.0254" />
    <TextItem Name="nom" X="0.7199" Y="0.7118" DataField="" DataFieldFormatString="" CacheItemId="" Comments="" Tag="" Width="6.3511" Height="1.3013" Text="null" Font="Agency FB,32,True,False,False,False,Point,,,False,90,,CP850" ForeColor="White" />
    <TextItem Name="wilaya" X="0.7019" Y="3.5635" DataField="" DataFieldFormatString="" CacheItemId="" Comments="" Tag="" Width="0.8924" Height="1.2532" Text="null" Font="Agency FB,32,True,False,True,False,Point,,,False,90,,CP850" ForeColor="White" />
    <TextItem Name="prenom" X="0.692" Y="2.0347" DataField="" DataFieldFormatString="" CacheItemId="" Comments="" Tag="" Width="6.3511" Height="1.3013" Text="null" Font="Agency FB,32,True,False,False,False,Point,,,False,90,,CP850" ForeColor="White" />
    <BarcodeItem Name="id" X="7.1528" Y="1.1049" DataField="" DataFieldFormatString="" CacheItemId="" Comments="" Tag="" Locked="True" Width="3.2279" Height="1.3758" Symbology="Code128" Code="" AddChecksum="False" AztecCodeModuleSize="0.105918" BarHeight="1.27" BarWidth="0.026416" BearerBarThickness="0.127" DataMatrixModuleSize="0.105918" EanUpcGuardBarHeight="1.397" EanUpcSupplementSeparation="0.381" EanUpcSupplementTopMargin="0.381" Font="NativePrinterFontA,10,Point,,,False,90,,CP850" PharmacodeBarsSpacing="0.105918" PharmacodeThickBarWidth="0.15875" PharmacodeThinBarWidth="0.052832" Postal4StateBarsSpacing="0.079502" Postal4StateTrackerBarHeight="0.2032" Postal4StateTrackerBarWidth="0.052832" QRCodeModuleSize="0.105918" QuietZone="0.254,0,0.254,0.050800000000000005" RotationAngle="90" Sizing="FitProportional" TextFont="NativePrinterFontA,10,Point,,,False,90,,CP850" HanXinCodeModuleSize="0.105918" MaxiCodeDrawPixelBasedSymbol="True" DotCodeModuleSize="0.105918" DotCodeAspectRatio="" />
    <TextItem Name="address" X="2.1605" Y="3.5487" DataField="" DataFieldFormatString="" CacheItemId="" Comments="" Tag="" Width="4.8864" Height="1.1266" Text="adress" Font="Agency FB,32,Point,,,False,90,,CP850" ForeColor="White" />
    <TextItem Name="" X="5.9204" Y="5.9021" DataField="" DataFieldFormatString="" CacheItemId="" Comments="" Tag="" Width="2.6026" Height="0.5696" Text="eurequat_x0020__x0040_2024" Font="Agency FB,14,False,False,True,False,Point,,,False,90,,CP850" />
    <TextItem Name="" X="3.0403" Y="4.867" DataField="" DataFieldFormatString="" CacheItemId="" Comments="" Tag="" Width="4.956" Height="1.0013" Text="https:_x002F__x002F_itstarik.me" Font="Agency FB,22,False,False,True,False,Point,,,False,90,,CP850" />
    <TextItem Name="" X="0.6427" Y="4.8437" DataField="" DataFieldFormatString="" CacheItemId="" Comments="" Tag="" Width="2.3659" Height="0.9735" Text="website:" Font="Agency FB,22,Point,,,False,90,,CP850" />
    <ImageItem Name="" X="4.9811" Y="0.2003" DataField="" DataFieldFormatString="" CacheItemId="" Comments="" Tag="" Width="2.0373" Height="2.0638" Source="File" SourceData="C:\Users\tarik\Downloads\favicon.jpg" MonochromeSettings="OtsuThreshold,50,False" />
    <BarcodeItem Name="" X="4.5601" Y="2.4777" DataField="" DataFieldFormatString="" CacheItemId="" Comments="" Tag="" Locked="True" Width="2.4871" Height="2.4871" Symbology="QRCode" Code="_x0031_23" AddChecksum="False" AztecCodeModuleSize="0.105918" BarHeight="1.27" BarWidth="0.026416" BearerBarThickness="0.127" DataMatrixModuleSize="0.105918" EanUpcGuardBarHeight="1.397" EanUpcSupplementSeparation="0.381" EanUpcSupplementTopMargin="0.381" Font="NativePrinterFontA,10,Point,,,False,90,,CP850" PharmacodeBarsSpacing="0.105918" PharmacodeThickBarWidth="0.15875" PharmacodeThinBarWidth="0.052832" PlanetHeightShortBar="0.64516" PlanetHeightTallBar="1.29032" Postal4StateBarsSpacing="0.079502" Postal4StateTrackerBarHeight="0.2032" Postal4StateTrackerBarWidth="0.052832" PostnetHeightShortBar="0.64516" PostnetHeightTallBar="1.29032" QRCodeModuleSize="0.105918" QuietZone="0.254,0,0.254,0.050800000000000005" Sizing="FitProportional" TextFont="NativePrinterFontA,10,Point,,,False,90,,CP850" HanXinCodeModuleSize="0.105918" MaxiCodeDrawPixelBasedSymbol="True" DotCodeModuleSize="0.105918" DotCodeAspectRatio="" />
  </Items>
</ThermalLabel>
